svvamp/__init__.py
svvamp/meta/experiment_analyzer.py
svvamp/meta/experiments_compiler.py
svvamp/meta/study_profile_criteria.py
svvamp/meta/study_rule_criteria.py
svvamp/meta/voting_rule_tasks.py
svvamp/preferences/__init__.py
svvamp/preferences/generator_profile.py
svvamp/preferences/generator_profile_cubic_uniform.py
svvamp/preferences/generator_profile_euclidean_box.py
svvamp/preferences/generator_profile_gaussian_well.py
svvamp/preferences/generator_profile_ianc.py
svvamp/preferences/generator_profile_ic.py
svvamp/preferences/generator_profile_ladder.py
svvamp/preferences/generator_profile_noise.py
svvamp/preferences/generator_profile_noised_file.py
svvamp/preferences/generator_profile_perturbed_culture.py
svvamp/preferences/generator_profile_spheroid.py
svvamp/preferences/generator_profile_unanimous.py
svvamp/preferences/generator_profile_vmf_hypercircle.py
svvamp/preferences/generator_profile_vmf_hypersphere.py
svvamp/preferences/plurality_elimination_engine.py
svvamp/preferences/plurality_elimination_engine_profile.py
svvamp/preferences/plurality_elimination_engine_profile_um.py
svvamp/preferences/profile.py
svvamp/preferences/profile_from_file.py
svvamp/preferences/profile_subset_candidates.py
svvamp/preferences/profile_um.py
svvamp/rules/all_rule_classes.py
svvamp/rules/rule.py
svvamp/rules/rule_approval.py
svvamp/rules/rule_baldwin.py
svvamp/rules/rule_black.py
svvamp/rules/rule_borda.py
svvamp/rules/rule_bucklin.py
svvamp/rules/rule_condorcet_abs_irv.py
svvamp/rules/rule_condorcet_sum_defeats.py
svvamp/rules/rule_condorcet_vtb_irv.py
svvamp/rules/rule_coombs.py
svvamp/rules/rule_copeland.py
svvamp/rules/rule_exhaustive_ballot.py
svvamp/rules/rule_icrv.py
svvamp/rules/rule_irv.py
svvamp/rules/rule_irv_average.py
svvamp/rules/rule_irv_duels.py
svvamp/rules/rule_iterated_bucklin.py
svvamp/rules/rule_k_approval.py
svvamp/rules/rule_kemeny.py
svvamp/rules/rule_kim_roush.py
svvamp/rules/rule_majority_judgment.py
svvamp/rules/rule_maximin.py
svvamp-0.12.0.dist-info/AUTHORS.md
svvamp-0.12.0.dist-info/LICENSE
svvamp-0.12.0.dist-info/METADATA
svvamp-0.12.0.dist-info/WHEEL
svvamp-0.12.0.dist-info/RECORD
