Metadata-Version: 2.3
Name: svvamp
Version: 0.12.0
Summary: Simulator of Various Voting Algorithms in Manipulating Populations
Author: François Durand
Author-email: fradurand@gmail.com
Requires-Python: >=3.10,<4.0
Classifier: Programming Language :: Python :: 3
Classifier: Programming Language :: Python :: 3.10
Classifier: Programming Language :: Python :: 3.11
Classifier: Programming Language :: Python :: 3.12
Classifier: Programming Language :: Python :: 3.13
Requires-Dist: matplotlib (>=3.10.0,<4.0.0)
Requires-Dist: networkx (>=3.4.2,<4.0.0)
Requires-Dist: numpy (>=2.2.3,<3.0.0)
Requires-Dist: pandas (>=2.2.3,<3.0.0)
Requires-Dist: tikzplotlib (>=0.10.1,<0.11.0)
Project-URL: Documentation, https://francois-durand.github.io/svvamp
Project-URL: Repository, https://github.com/francois-durand/svvamp
